.DS_Store
.gitignore
LICENSE
README.md
cutils.cpython-38-darwin.so
project.toml
requirements.txt
setup.cfg
setup.py
.github/workflows/python-package.yml
.github/workflows/python-publish.yml
.vscode/c_cpp_properties.json
TuoTuo.egg-info/PKG-INFO
TuoTuo.egg-info/SOURCES.txt
TuoTuo.egg-info/dependency_links.txt
TuoTuo.egg-info/requires.txt
TuoTuo.egg-info/top_level.txt
notebook/Our Model vs SKLearn.ipynb
notebook/__init__.py
tuotuo/__init__.py
tuotuo/cutils.c
tuotuo/cutils.cpython-38-darwin.so
tuotuo/cutils.pyx
tuotuo/generator.py
tuotuo/lda_model.py
tuotuo/text_pre_processor.py
tuotuo/utils.py
tuotuo.egg-info/PKG-INFO
tuotuo.egg-info/SOURCES.txt
tuotuo.egg-info/dependency_links.txt
tuotuo.egg-info/requires.txt
tuotuo.egg-info/top_level.txt
tuotuo/build/lib.macosx-10.14-arm64-cpython-38/cutils.cpython-38-darwin.so
tuotuo/build/temp.macosx-10.14-arm64-cpython-38/cutils.o