Metadata-Version: 2.1
Name: TuoTuo
Version: 0.1.6
Summary: LDA & Neura based topic modelling library
Home-page: https://github.com/RobbenRibery/TuoTuo
Download-URL: https://github.com/RobbenRibery/TuoTuo/archive/refs/tags/Pypi-0.0.5.tar.gz
Author: tuotuo Superman
Author-email: tuotuo@HanwellSquare.BigForce.com
License: MIT
Keywords: Generative Topic Modelling,Latent Dirichlet Allocation
Classifier: Development Status :: 3 - Alpha
Classifier: Intended Audience :: Science/Research
Classifier: Topic :: Scientific/Engineering :: Artificial Intelligence
Classifier: License :: OSI Approved :: MIT License
Classifier: Programming Language :: Python :: 3.8
Classifier: Programming Language :: Python :: 3.9
Classifier: Programming Language :: Python :: 3.10
License-File: LICENSE
